GDNox/__init__.py
GDNox/behavior/__init__.py
GDNox/behavior/mouse.py
GDNox/core/__init__.py
GDNox/core/browser.py
GDNox/core/cdp_client.py
GDNox/core/element.py
GDNox/core/network.py
GDNox/core/tab.py
GDNox/shadow/__init__.py
GDNox/shadow/shadow_root.py
GDNox/stealth/__init__.py
GDNox/stealth/fingerprint.py
GDNox/stealth/profile.py
GDNox/stealth/runtime_patches.py
GDNox/utils/__init__.py
GDNox/utils/chrome_finder.py
gdnox-0.1.1.dist-info/LICENSE
gdnox-0.1.1.dist-info/METADATA
gdnox-0.1.1.dist-info/WHEEL
gdnox-0.1.1.dist-info/RECORD
