Metadata-Version: 2.1
Name: gdnox
Version: 0.1.1
Summary: Undetectable browser automation library with stealth features, closed Shadow DOM access, and antibot bypass capabilities
Home-page: https://github.com/rafaelgdn/GDNox
License: PolyForm-Noncommercial-1.0.0
Keywords: browser-automation,stealth,antibot,cloudflare,turnstile,captcha,cdp,chrome-devtools-protocol,shadow-dom,web-scraping
Author: Rafael
Author-email: rafaeldecarvalho.ps@gmail.com
Requires-Python: >=3.10,<4.0
Classifier: Development Status :: 4 - Beta
Classifier: Framework :: AsyncIO
Classifier: Intended Audience :: Developers
Classifier: License :: Other/Proprietary License
Classifier: Programming Language :: Python :: 3
Classifier: Programming Language :: Python :: 3.10
Classifier: Programming Language :: Python :: 3.11
Classifier: Programming Language :: Python :: 3.12
Classifier: Programming Language :: Python :: 3.13
Classifier: Topic :: Internet :: WWW/HTTP :: Browsers
Classifier: Topic :: Software Development :: Libraries :: Python Modules
Classifier: Topic :: Software Development :: Testing
Requires-Dist: aiohttp (>=3.13.2,<4.0.0)
Requires-Dist: websockets (>=12.0)
Project-URL: Repository, https://github.com/rafaelgdn/GDNox
